README.md
setup.py
dreamerv2/agent.py
dreamerv2/api.py
dreamerv2/configs.yaml
dreamerv2/expl.py
dreamerv2/train.py
dreamerv2.egg-info/PKG-INFO
dreamerv2.egg-info/SOURCES.txt
dreamerv2.egg-info/dependency_links.txt
dreamerv2.egg-info/entry_points.txt
dreamerv2.egg-info/requires.txt
dreamerv2.egg-info/top_level.txt
dreamerv2/common/__init__.py
dreamerv2/common/config.py
dreamerv2/common/counter.py
dreamerv2/common/dists.py
dreamerv2/common/driver.py
dreamerv2/common/envs.py
dreamerv2/common/flags.py
dreamerv2/common/logger.py
dreamerv2/common/nets.py
dreamerv2/common/other.py
dreamerv2/common/plot.py
dreamerv2/common/replay.py
dreamerv2/common/tfutils.py
dreamerv2/common/when.py