Metadata-Version: 2.1
Name: dreamerv2
Version: 2.0.9
Summary: Mastering Atari with Discrete World Models
Home-page: http://github.com/danijar/dreamerv2
License: UNKNOWN
Platform: UNKNOWN
Classifier: Intended Audience :: Science/Research
Classifier: License :: OSI Approved :: MIT License
Classifier: Programming Language :: Python :: 3
Classifier: Topic :: Games/Entertainment
Classifier: Topic :: Scientific/Engineering :: Artificial Intelligence
